dbutilsx/__init__.py
dbutilsx/persistent_db.py
dbutilsx/pooled_db.py
dbutilsx/dbutils/__init__.py
dbutilsx/dbutils/persistent_db.py
dbutilsx/dbutils/pooled_db.py
dbutilsx/dbutils/steady_db.py
rdsdriver/__init__.py
rdsdriver/dm/__init__.py
rdsdriver/dm/dm.py
rdsdriver/dm/dmPython.cpython-36-aarch64-linux-gnu.so
rdsdriver/dm/dmPython.cpython-36-x86_64-linux-gnu.so
rdsdriver/dm/dmPython.cpython-38-aarch64-linux-gnu.so
rdsdriver/dm/dmPython.cpython-38-x86_64-linux-gnu.so
rdsdriver/mysql/__init__.py
rdsdriver/mysql/mysql.py
DBUtilsX-1.3.3.dist-info/METADATA
DBUtilsX-1.3.3.dist-info/WHEEL
DBUtilsX-1.3.3.dist-info/top_level.txt
DBUtilsX-1.3.3.dist-info/RECORD
